{
	"storyName": "zomygod",
	"difficulties": "hard",
	"hideFreeplay": false,
	"weekBackground": "",
	"freeplayColor": [
		146,
		113,
		253
	],
	"weekBefore": "tutorial",
	"startUnlocked": true,
	"weekCharacters": [
		"",
		"",
		""
	],
	"songs": [
		[
			"bijuu",
			"bijuu",
			[
				146,
				113,
				253
			]
		],
		[
			"holyshitdavefnf",
			"dave",
			[
				146,
				113,
				253
			]
		],
		[
			"bloodbath",
			"demonron",
			[
				146,
				113,
				253
			]
		],
		[
			"bleeding",
			"ron-bloodshed",
			[
				146,
				113,
				253
			]
		],
		[
			"bloodshed-old",
			"ron-bloodshed",
			[
				146,
				113,
				253
			]
		]
	],
	"hideStoryMode": false,
	"weekName": "Custom Week"
}